{"#scalarizations": {"first_stage": 26, "infeasible": 8, "no_warm_start": 17, "second_stage": 18, "third_stage": 15, "total": 59}, "0": {"#nondominated": 2, "#scalarizations": {"first_stage": 4, "infeasible": 1, "no_warm_start": 3, "second_stage": 3, "third_stage": 3, "total": 10}}, "1": {"#nondominated": 0, "#scalarizations": {"first_stage": 0, "infeasible": 0, "no_warm_start": 0, "second_stage": 0, "third_stage": 0, "total": 0}}, "10": {"#nondominated": 0, "#scalarizations": {"first_stage": 0, "infeasible": 0, "no_warm_start": 0, "second_stage": 0, "third_stage": 0, "total": 0}}, "11": {"#nondominated": 2, "#scalarizations": {"first_stage": 3, "infeasible": 1, "no_warm_start": 3, "second_stage": 2, "third_stage": 2, "total": 7}}, "12": {"#nondominated": 0, "#scalarizations": {"first_stage": 0, "infeasible": 0, "no_warm_start": 0, "second_stage": 0, "third_stage": 0, "total": 0}}, "13": {"#nondominated": 2, "#scalarizations": {"first_stage": 3, "infeasible": 1, "no_warm_start": 1, "second_stage": 2, "third_stage": 0, "total": 5}}, "14": {"#nondominated": 0, "#scalarizations": {"first_stage": 0, "infeasible": 0, "no_warm_start": 0, "second_stage": 0, "third_stage": 0, "total": 0}}, "15": {"#nondominated": 0, "#scalarizations": {"first_stage": 0, "infeasible": 0, "no_warm_start": 0, "second_stage": 0, "third_stage": 0, "total": 0}}, "2": {"#nondominated": 1, "#scalarizations": {"first_stage": 2, "infeasible": 1, "no_warm_start": 2, "second_stage": 1, "third_stage": 1, "total": 4}}, "3": {"#nondominated": 0, "#scalarizations": {"first_stage": 0, "infeasible": 0, "no_warm_start": 0, "second_stage": 0, "third_stage": 0, "total": 0}}, "4": {"#nondominated": 0, "#scalarizations": {"first_stage": 0, "infeasible": 0, "no_warm_start": 0, "second_stage": 0, "third_stage": 0, "total": 0}}, "5": {"#nondominated": 0, "#scalarizations": {"first_stage": 4, "infeasible": 3, "no_warm_start": 4, "second_stage": 1, "third_stage": 1, "total": 6}}, "6": {"#nondominated": 2, "#scalarizations": {"first_stage": 3, "infeasible": 1, "no_warm_start": 3, "second_stage": 2, "third_stage": 2, "total": 7}}, "7": {"#nondominated": 0, "#scalarizations": {"first_stage": 0, "infeasible": 0, "no_warm_start": 0, "second_stage": 0, "third_stage": 0, "total": 0}}, "8": {"#nondominated": 0, "#scalarizations": {"first_stage": 0, "infeasible": 0, "no_warm_start": 0, "second_stage": 0, "third_stage": 0, "total": 0}}, "9": {"#nondominated": 0, "#scalarizations": {"first_stage": 7, "infeasible": 0, "no_warm_start": 1, "second_stage": 7, "third_stage": 6, "total": 20}}, "Y_N": [[30, 37, 30], [29, 43, 30], [39, 32, 48], [32, 37, 29], [40, 27, 35], [31, 38, 21], [42, 22, 26], [18, 48, 36], [27, 38, 42]], "cpu(micro_s)": 79283, "cpu_init(micro_s)": 40732, "instanz": "AP_p-3_n-5_ins-10_threads-16.json", "threads": 16, "|Y_N3|": 6, "|Y_N|": 9}